xrview/__init__.py
xrview/elements.py
xrview/glyphs.py
xrview/handlers.py
xrview/interactions.py
xrview/mappers.py
xrview/palettes.py
xrview/timeseries.py
xrview/utils.py
xrview/core/__init__.py
xrview/core/panel.py
xrview/core/plot.py
xrview/core/viewer.py
xrview/html/__init__.py
xrview/html/base.py
xrview/notebook/__init__.py
xrview/notebook/base.py
xrview/notebook/sidecar.py
xrview/notebook/utils.py
xrview-0.1.0.dist-info/AUTHORS.rst
xrview-0.1.0.dist-info/LICENSE
xrview-0.1.0.dist-info/METADATA
xrview-0.1.0.dist-info/WHEEL
xrview-0.1.0.dist-info/top_level.txt
xrview-0.1.0.dist-info/RECORD
