Metadata-Version: 2.1
Name: xrview
Version: 0.1.0
Summary: Visualizing xarray data.
Home-page: https://github.com/phausamann/xrview
Author: Peter Hausamann
Author-email: peter.hausamann@tum.de
License: MIT license
Keywords: xrview
Platform: UNKNOWN
Classifier: Development Status :: 2 - Pre-Alpha
Classifier: Intended Audience :: Developers
Classifier: License :: OSI Approved :: MIT License
Classifier: Natural Language :: English
Classifier: Programming Language :: Python :: 3
Classifier: Programming Language :: Python :: 3.4
Classifier: Programming Language :: Python :: 3.5
Classifier: Programming Language :: Python :: 3.6
Requires-Dist: numpy
Requires-Dist: pandas
Requires-Dist: xarray (>=0.10)
Requires-Dist: bokeh (>=1.4)
Requires-Dist: six
